mailinglist/__init__.py
mailinglist/admin.py
mailinglist/admin_forms.py
mailinglist/apps.py
mailinglist/conf.py
mailinglist/enum.py
mailinglist/forms.py
mailinglist/hooks.py
mailinglist/models.py
mailinglist/services.py
mailinglist/tasks.py
mailinglist/urls.py
mailinglist/views.py
mailinglist/addressimport/__init__.py
mailinglist/addressimport/parsers.py
mailinglist/management/__init__.py
mailinglist/management/commands/__init__.py
mailinglist/management/commands/process_submissions.py
mailinglist/migrations/0001_initial.py
mailinglist/migrations/0002_messageattachment.py
mailinglist/migrations/0003_alter_messagepart_options.py
mailinglist/migrations/__init__.py
mailinglist/templates/admin/mailinglist/preview.html
mailinglist/templates/admin/mailinglist/message/change_form.html
mailinglist/templates/admin/mailinglist/submission/change_form.html
mailinglist/templates/admin/mailinglist/subscription/change_list.html
mailinglist/templates/admin/mailinglist/subscription/confirm_import_form.html
mailinglist/templates/admin/mailinglist/subscription/import_form.html
mailinglist/templates/mailinglist/email/message.html
mailinglist/templates/mailinglist/email/message.txt
mailinglist/templates/mailinglist/email/message_subject.txt
mailinglist/templates/mailinglist/email/subscribe.html
mailinglist/templates/mailinglist/email/subscribe.txt
mailinglist/templates/mailinglist/email/subscribe_subject.txt
mailinglist/templates/mailinglist/email/global-deny/subscribe.html
mailinglist/templates/mailinglist/email/global-deny/subscribe.txt
mailinglist/templates/mailinglist/email/global-deny/subscribe_subject.txt
mailinglist/templates/mailinglist/web/global_unsubscribe.html
mailinglist/templates/mailinglist/web/global_unsubscribe_success.html
mailinglist/templates/mailinglist/web/subscribe.html
mailinglist/templates/mailinglist/web/subscribe_confirm.html
mailinglist/templates/mailinglist/web/subscribe_success.html
mailinglist/templates/mailinglist/web/subscriptions.html
django_mailinglist-0.1.7.dist-info/LICENSE.txt
django_mailinglist-0.1.7.dist-info/METADATA
django_mailinglist-0.1.7.dist-info/WHEEL
django_mailinglist-0.1.7.dist-info/top_level.txt
django_mailinglist-0.1.7.dist-info/RECORD
