Metadata-Version: 2.1
Name: django-mailinglist
Version: 0.1.7
Summary: Django app for managing multiple mailing lists with both plaintext as well as HTML templates (facilitated by Markdown).
Home-page: http://github.com/thismatters/django-mailinglist/
Author: Paul Stiverson
Author-email: paul@thismatters.net
Classifier: Development Status :: 3 - Alpha
Classifier: Environment :: Web Environment
Classifier: Framework :: Django
Classifier: Framework :: Django :: 3.2
Classifier: Framework :: Django :: 4.1
Classifier: Framework :: Django :: 4.2
Classifier: Intended Audience :: Developers
Classifier: License :: OSI Approved :: GNU Affero General Public License v3
Classifier: Operating System :: OS Independent
Classifier: Programming Language :: Python
Classifier: Programming Language :: Python :: 3
Classifier: Programming Language :: Python :: 3.8
Classifier: Programming Language :: Python :: 3.9
Classifier: Programming Language :: Python :: 3.10
Classifier: Programming Language :: Python :: 3.11
Classifier: Programming Language :: Python :: 3.12
Classifier: Programming Language :: Python :: 3 :: Only
Classifier: Topic :: Utilities
Requires-Python: >=3.8
License-File: LICENSE.txt
Requires-Dist: Django >=3.2.0
Requires-Dist: Markdown >=3.3.0
Requires-Dist: django-enumfield >=3.0
Requires-Dist: django-appconf >=1.0.0
